LICENSE
README.md
setup.cfg
setup.py
salt_ttp/__init__.py
salt_ttp/loader.py
salt_ttp.egg-info/PKG-INFO
salt_ttp.egg-info/SOURCES.txt
salt_ttp.egg-info/dependency_links.txt
salt_ttp.egg-info/entry_points.txt
salt_ttp.egg-info/top_level.txt
salt_ttp/modules/__init__.py
salt_ttp/modules/ttp_execution_module.py
salt_ttp/runners/__init__.py
salt_ttp/runners/ttp_runner_module.py