Metadata-Version: 2.1
Name: salt-ttp
Version: 0.1.0
Summary: SALTSTACK TTP Modules
Home-page: https://github.com/dmulyalin/salt-ttp
Author: Denis Mulyalin
Author-email: d.mulyalin@gmail.com
License: UNKNOWN
Platform: UNKNOWN
Classifier: Topic :: Utilities
Classifier: Programming Language :: Python :: 2.7
Classifier: Programming Language :: Python :: 3.5
Classifier: Programming Language :: Python :: 3.6
Classifier: Programming Language :: Python :: 3.7
Classifier: License :: OSI Approved :: MIT License
Classifier: Operating System :: OS Independent
Requires-Python: >=3.6
